{
 "Name": "Dhl-Parckage.exe",
 "Md5": "c23ddfd819730d601349a384da8155a8",
 "UUID": "27be017c-e3d4-4d4c-a50b-ab7a56e8b842",
 "Processes": [
  {
   "OID": "5c7de9aad055db7f592ff497",
   "ProcessID": 3632,
   "ParentPID": 284,
   "CommandLine": "\"C:\\Users\\admin\\AppData\\Local\\Temp\\Dhl-Parckage.exe\" ",
   "Image": "C:\\Users\\admin\\AppData\\Local\\Temp\\Dhl-Parckage.exe",
   "ProcessType": "Main process",
   "CreationTimestamp": 1551755690006
  },
  {
   "OID": "5c7de9cfd055db7f592ffb14",
   "ProcessID": 2224,
   "ParentPID": 3632,
   "CommandLine": "\"C:\\Users\\admin\\AppData\\Local\\Temp\\Dhl-Parckage.exe\"",
   "Image": "C:\\Users\\admin\\AppData\\Local\\Temp\\Dhl-Parckage.exe",
   "ProcessType": "Child process",
   "CreationTimestamp": 1551755726678
  },
  {
   "OID": "5c7de9cfd055db7f592ffb15",
   "ProcessID": 3380,
   "ParentPID": 2224,
   "CommandLine": "\"C:\\Windows\\System32\\WScript.exe\" \"C:\\Users\\admin\\AppData\\Local\\Temp\\install.vbs\" ",
   "Image": "C:\\Windows\\System32\\WScript.exe",
   "ProcessType": "Child process",
   "CreationTimestamp": 1551755726975
  },
  {
   "OID": "5c7de9d0d055db7f59300164",
   "ProcessID": 2736,
   "ParentPID": 3380,
   "CommandLine": "\"C:\\Windows\\System32\\cmd.exe\" /c \"C:\\Users\\admin\\AppData\\Roaming\\mcos\\tycos.exe\"",
   "Image": "C:\\Windows\\System32\\cmd.exe",
   "ProcessType": "Child process",
   "CreationTimestamp": 1551755728428
  },
  {
   "OID": "5c7de9d0d055db7f59300166",
   "ProcessID": 3308,
   "ParentPID": 2736,
   "CommandLine": "C:\\Users\\admin\\AppData\\Roaming\\mcos\\tycos.exe",
   "Image": "C:\\Users\\admin\\AppData\\Roaming\\mcos\\tycos.exe",
   "ProcessType": "Child process",
   "CreationTimestamp": 1551755728491
  },
  {
   "OID": "5c7de9f5d055db7f59300ad1",
   "ProcessID": 2244,
   "ParentPID": 3308,
   "CommandLine": "\"C:\\Users\\admin\\AppData\\Roaming\\mcos\\tycos.exe\"",
   "Image": "C:\\Users\\admin\\AppData\\Roaming\\mcos\\tycos.exe",
   "ProcessType": "Child process",
   "CreationTimestamp": 1551755764819
  }
 ],
 "Incidents": [
  {
   "ProcessOID": "5c7de9f5d055db7f59300ad1",
   "ThreatLevel": 1,
   "MitreAttacks": []
  },
  {
   "ProcessOID": "5c7de9f5d055db7f59300ad1",
   "ThreatLevel": 1,
   "MitreAttacks": []
  },
  {
   "ProcessOID": "5c7de9f5d055db7f59300ad1",
   "ThreatLevel": 2,
   "MitreAttacks": []
  },
  {
   "ProcessOID": "5c7de9f5d055db7f59300ad1",
   "ThreatLevel": 1,
   "MitreAttacks": [
    "T1065"
   ]
  },
  {
   "ProcessOID": "5c7de9f5d055db7f59300ad1",
   "ThreatLevel": 2,
   "MitreAttacks": [
    "T1060"
   ]
  },
  {
   "ProcessOID": "5c7de9d0d055db7f59300166",
   "ThreatLevel": 1,
   "MitreAttacks": [
    "T1106"
   ]
  },
  {
   "ProcessOID": "5c7de9cfd055db7f592ffb15",
   "ThreatLevel": 1,
   "MitreAttacks": [
    "T1059"
   ]
  },
  {
   "ProcessOID": "5c7de9cfd055db7f592ffb14",
   "ThreatLevel": 1,
   "MitreAttacks": [
    "T1064"
   ]
  },
  {
   "ProcessOID": "5c7de9cfd055db7f592ffb14",
   "ThreatLevel": 2,
   "MitreAttacks": [
    "T1060"
   ]
  },
  {
   "ProcessOID": "5c7de9cfd055db7f592ffb14",
   "ThreatLevel": 1,
   "MitreAttacks": []
  },
  {
   "ProcessOID": "5c7de9cfd055db7f592ffb14",
   "ThreatLevel": 1,
   "MitreAttacks": []
  },
  {
   "ProcessOID": "5c7de9aad055db7f592ff497",
   "ThreatLevel": 1,
   "MitreAttacks": [
    "T1106"
   ]
  }
 ]
}