{
 "Name": "MinecraftDungeonsCRACK.exe",
 "Md5": "31d50351bc2704254e3a8f0ad9cda110",
 "UUID": "2c164b09-27e8-409f-a0d4-ec05b85ed68d",
 "Processes": [
  {
   "OID": "5f1361807dd55c5053986f7a",
   "ProcessID": 960,
   "ParentPID": 392,
   "CommandLine": "\"C:\\Users\\admin\\AppData\\Local\\Temp\\MinecraftDungeonsCRACK.exe\" ",
   "Image": "C:\\Users\\admin\\AppData\\Local\\Temp\\MinecraftDungeonsCRACK.exe",
   "ProcessType": "Main process",
   "CreationTimestamp": 1595105664323
  },
  {
   "OID": "5f1361807dd55c5053986f7b",
   "ProcessID": 1544,
   "ParentPID": 960,
   "CommandLine": "\"C:\\Windows\\System32\\eventvwr.exe\" ",
   "Image": "C:\\Windows\\System32\\eventvwr.exe",
   "ProcessType": "Child process",
   "CreationTimestamp": 1595105664636
  },
  {
   "OID": "5f1361827dd55c5053987476",
   "ProcessID": 2404,
   "ParentPID": 960,
   "CommandLine": "\"C:\\Windows\\System32\\eventvwr.exe\" ",
   "Image": "C:\\Windows\\System32\\eventvwr.exe",
   "ProcessType": "Child process",
   "CreationTimestamp": 1595105665808
  },
  {
   "OID": "5f1361827dd55c5053987477",
   "ProcessID": 3348,
   "ParentPID": 2404,
   "CommandLine": "\"C:\\Users\\admin\\AppData\\Local\\Temp\\MinecraftDungeonsCRACK.exe\" ",
   "Image": "C:\\Users\\admin\\AppData\\Local\\Temp\\MinecraftDungeonsCRACK.exe",
   "ProcessType": "Child process",
   "CreationTimestamp": 1595105665917
  },
  {
   "OID": "5f1361827dd55c5053987478",
   "ProcessID": 1288,
   "ParentPID": 3348,
   "CommandLine": "/k %windir%\\System32\\reg.exe ADD HKLM\\SOFTWARE\\Microsoft\\Windows\\CurrentVersion\\Policies\\System /v EnableLUA /t REG_DWORD /d 0 /f",
   "Image": "C:\\Windows\\System32\\cmd.exe",
   "ProcessType": "Child process",
   "CreationTimestamp": 1595105665980
  },
  {
   "OID": "5f1361827dd55c505398747a",
   "ProcessID": 2696,
   "ParentPID": 1288,
   "CommandLine": "C:\\Windows\\System32\\reg.exe  ADD HKLM\\SOFTWARE\\Microsoft\\Windows\\CurrentVersion\\Policies\\System /v EnableLUA /t REG_DWORD /d 0 /f",
   "Image": "C:\\Windows\\System32\\reg.exe",
   "ProcessType": "Child process",
   "CreationTimestamp": 1595105666027
  },
  {
   "OID": "5f1361827dd55c505398747b",
   "ProcessID": 3608,
   "ParentPID": 3348,
   "CommandLine": "cmd /c \"\"C:\\Users\\admin\\AppData\\Local\\Temp\\install.bat\" \"",
   "Image": "C:\\Windows\\system32\\cmd.exe",
   "ProcessType": "Child process",
   "CreationTimestamp": 1595105666198
  },
  {
   "OID": "5f1361827dd55c505398747d",
   "ProcessID": 2512,
   "ParentPID": 3608,
   "CommandLine": "PING  127.0.0.1 -n 2 ",
   "Image": "C:\\Windows\\system32\\PING.EXE",
   "ProcessType": "Child process",
   "CreationTimestamp": 1595105666261
  },
  {
   "OID": "5f1361847dd55c5053988213",
   "ProcessID": 2576,
   "ParentPID": 3608,
   "CommandLine": "\"C:\\Users\\admin\\AppData\\Roaming\\WindowsFiles32b\\remcos.exe\" ",
   "Image": "C:\\Users\\admin\\AppData\\Roaming\\WindowsFiles32b\\remcos.exe",
   "ProcessType": "Child process",
   "CreationTimestamp": 1595105667464
  },
  {
   "OID": "5f1361847dd55c5053988214",
   "ProcessID": 2076,
   "ParentPID": 2576,
   "CommandLine": "/k %windir%\\System32\\reg.exe ADD HKLM\\SOFTWARE\\Microsoft\\Windows\\CurrentVersion\\Policies\\System /v EnableLUA /t REG_DWORD /d 0 /f",
   "Image": "C:\\Windows\\System32\\cmd.exe",
   "ProcessType": "Child process",
   "CreationTimestamp": 1595105667589
  },
  {
   "OID": "5f1361847dd55c5053988216",
   "ProcessID": 2188,
   "ParentPID": 2576,
   "CommandLine": "\"C:\\Program Files\\Internet Explorer\\iexplore.exe\"",
   "Image": "C:\\Program Files\\Internet Explorer\\iexplore.exe",
   "ProcessType": "Child process",
   "CreationTimestamp": 1595105667620
  },
  {
   "OID": "5f1361847dd55c5053988217",
   "ProcessID": 2680,
   "ParentPID": 2076,
   "CommandLine": "C:\\Windows\\System32\\reg.exe  ADD HKLM\\SOFTWARE\\Microsoft\\Windows\\CurrentVersion\\Policies\\System /v EnableLUA /t REG_DWORD /d 0 /f",
   "Image": "C:\\Windows\\System32\\reg.exe",
   "ProcessType": "Child process",
   "CreationTimestamp": 1595105667698
  },
  {
   "OID": "5f1361847dd55c5053988218",
   "ProcessID": 3452,
   "ParentPID": 2188,
   "CommandLine": "/k %windir%\\System32\\reg.exe ADD HKLM\\SOFTWARE\\Microsoft\\Windows\\CurrentVersion\\Policies\\System /v EnableLUA /t REG_DWORD /d 0 /f",
   "Image": "C:\\Windows\\System32\\cmd.exe",
   "ProcessType": "Child process",
   "CreationTimestamp": 1595105667761
  },
  {
   "OID": "5f1361847dd55c50539884c2",
   "ProcessID": 1480,
   "ParentPID": 3452,
   "CommandLine": "C:\\Windows\\System32\\reg.exe  ADD HKLM\\SOFTWARE\\Microsoft\\Windows\\CurrentVersion\\Policies\\System /v EnableLUA /t REG_DWORD /d 0 /f",
   "Image": "C:\\Windows\\System32\\reg.exe",
   "ProcessType": "Child process",
   "CreationTimestamp": 1595105667823
  },
  {
   "OID": "5f13618c7dd55c505398898c",
   "ProcessID": 760,
   "ParentPID": 2188,
   "CommandLine": "cmd /c \"\"C:\\Users\\admin\\AppData\\Local\\Temp\\uninstall.bat\" \"",
   "Image": "C:\\Windows\\system32\\cmd.exe",
   "ProcessType": "Child process",
   "CreationTimestamp": 1595105675761
  }
 ],
 "Incidents": [
  {
   "ProcessOID": "5f1361847dd55c50539884c2",
   "ThreatLevel": 2,
   "MitreAttacks": [
    "T1089"
   ]
  },
  {
   "ProcessOID": "5f1361847dd55c5053988218",
   "ThreatLevel": 1,
   "MitreAttacks": [
    "T1112",
    "T1012"
   ]
  },
  {
   "ProcessOID": "5f1361847dd55c5053988217",
   "ThreatLevel": 2,
   "MitreAttacks": [
    "T1089"
   ]
  },
  {
   "ProcessOID": "5f1361847dd55c5053988216",
   "ThreatLevel": 2,
   "MitreAttacks": []
  },
  {
   "ProcessOID": "5f1361847dd55c5053988216",
   "ThreatLevel": 2,
   "MitreAttacks": [
    "T1059"
   ]
  },
  {
   "ProcessOID": "5f1361847dd55c5053988214",
   "ThreatLevel": 1,
   "MitreAttacks": [
    "T1112",
    "T1012"
   ]
  },
  {
   "ProcessOID": "5f1361847dd55c5053988213",
   "ThreatLevel": 1,
   "MitreAttacks": []
  },
  {
   "ProcessOID": "5f1361847dd55c5053988213",
   "ThreatLevel": 2,
   "MitreAttacks": []
  },
  {
   "ProcessOID": "5f1361847dd55c5053988213",
   "ThreatLevel": 2,
   "MitreAttacks": [
    "T1060"
   ]
  },
  {
   "ProcessOID": "5f1361847dd55c5053988213",
   "ThreatLevel": 1,
   "MitreAttacks": [
    "T1059"
   ]
  },
  {
   "ProcessOID": "5f1361827dd55c505398747b",
   "ThreatLevel": 2,
   "MitreAttacks": []
  },
  {
   "ProcessOID": "5f1361827dd55c505398747a",
   "ThreatLevel": 2,
   "MitreAttacks": [
    "T1089"
   ]
  },
  {
   "ProcessOID": "5f1361827dd55c5053987478",
   "ThreatLevel": 1,
   "MitreAttacks": [
    "T1112",
    "T1012"
   ]
  },
  {
   "ProcessOID": "5f1361827dd55c5053987477",
   "ThreatLevel": 1,
   "MitreAttacks": []
  },
  {
   "ProcessOID": "5f1361827dd55c5053987477",
   "ThreatLevel": 2,
   "MitreAttacks": [
    "T1060"
   ]
  },
  {
   "ProcessOID": "5f1361827dd55c5053987477",
   "ThreatLevel": 2,
   "MitreAttacks": []
  },
  {
   "ProcessOID": "5f1361827dd55c5053987477",
   "ThreatLevel": 1,
   "MitreAttacks": [
    "T1042"
   ]
  },
  {
   "ProcessOID": "5f1361827dd55c5053987477",
   "ThreatLevel": 2,
   "MitreAttacks": [
    "T1088"
   ]
  },
  {
   "ProcessOID": "5f1361827dd55c5053987477",
   "ThreatLevel": 1,
   "MitreAttacks": []
  },
  {
   "ProcessOID": "5f1361827dd55c5053987477",
   "ThreatLevel": 1,
   "MitreAttacks": [
    "T1059"
   ]
  },
  {
   "ProcessOID": "5f1361807dd55c5053986f7a",
   "ThreatLevel": 1,
   "MitreAttacks": [
    "T1042"
   ]
  },
  {
   "ProcessOID": "5f1361807dd55c5053986f7a",
   "ThreatLevel": 2,
   "MitreAttacks": [
    "T1088"
   ]
  },
  {
   "ProcessOID": "5f1361807dd55c5053986f7a",
   "ThreatLevel": 2,
   "MitreAttacks": []
  }
 ]
}