{
 "Name": "19d1c400-87bf-4416-944a-c9bc9fb5c406",
 "Md5": "14c602307ea33b5b3b359561a5b0090c",
 "UUID": "b533b490-5f90-480a-bbf6-10a041a3b38b",
 "Processes": [
  {
   "OID": "5e9b57866fb31c7e65e55153",
   "ProcessID": 1852,
   "ParentPID": 372,
   "CommandLine": "\"C:\\Users\\admin\\AppData\\Local\\Temp\\19d1c400-87bf-4416-944a-c9bc9fb5c406.exe\" ",
   "Image": "C:\\Users\\admin\\AppData\\Local\\Temp\\19d1c400-87bf-4416-944a-c9bc9fb5c406.exe",
   "ProcessType": "Main process",
   "CreationTimestamp": 1587238789660
  },
  {
   "OID": "5e9b57c76fb31c7e65e55665",
   "ProcessID": 3212,
   "ParentPID": 1852,
   "CommandLine": "C:\\Users\\admin\\AppData\\Local\\Temp\\19d1c400-87bf-4416-944a-c9bc9fb5c406.exe",
   "Image": "C:\\Users\\admin\\AppData\\Local\\Temp\\19d1c400-87bf-4416-944a-c9bc9fb5c406.exe",
   "ProcessType": "Child process",
   "CreationTimestamp": 1587238855441
  },
  {
   "OID": "5e9b57c76fb31c7e65e55666",
   "ProcessID": 3668,
   "ParentPID": 3212,
   "CommandLine": "\"C:\\Windows\\System32\\WScript.exe\" \"C:\\Users\\admin\\AppData\\Local\\Temp\\install.vbs\" ",
   "Image": "C:\\Windows\\System32\\WScript.exe",
   "ProcessType": "Child process",
   "CreationTimestamp": 1587238855691
  },
  {
   "OID": "5e9b57c96fb31c7e65e55d24",
   "ProcessID": 3408,
   "ParentPID": 3668,
   "CommandLine": "\"C:\\Windows\\System32\\cmd.exe\" /c \"C:\\Users\\admin\\AppData\\Roaming\\System32\\PServicesNet.exe\"",
   "Image": "C:\\Windows\\System32\\cmd.exe",
   "ProcessType": "Child process",
   "CreationTimestamp": 1587238856894
  },
  {
   "OID": "5e9b57c96fb31c7e65e55d26",
   "ProcessID": 1028,
   "ParentPID": 3408,
   "CommandLine": "C:\\Users\\admin\\AppData\\Roaming\\System32\\PServicesNet.exe",
   "Image": "C:\\Users\\admin\\AppData\\Roaming\\System32\\PServicesNet.exe",
   "ProcessType": "Child process",
   "CreationTimestamp": 1587238856957
  },
  {
   "OID": "5e9b57f06fb31c7e65e56364",
   "ProcessID": 2520,
   "ParentPID": 1028,
   "CommandLine": "C:\\Users\\admin\\AppData\\Roaming\\System32\\PServicesNet.exe",
   "Image": "C:\\Users\\admin\\AppData\\Roaming\\System32\\PServicesNet.exe",
   "ProcessType": "Child process",
   "CreationTimestamp": 1587238895519
  }
 ],
 "Incidents": [
  {
   "ProcessOID": "5e9b57f06fb31c7e65e56364",
   "ThreatLevel": 1,
   "MitreAttacks": [
    "T1056"
   ]
  },
  {
   "ProcessOID": "5e9b57f06fb31c7e65e56364",
   "ThreatLevel": 1,
   "MitreAttacks": []
  },
  {
   "ProcessOID": "5e9b57f06fb31c7e65e56364",
   "ThreatLevel": 1,
   "MitreAttacks": [
    "T1065"
   ]
  },
  {
   "ProcessOID": "5e9b57f06fb31c7e65e56364",
   "ThreatLevel": 2,
   "MitreAttacks": []
  },
  {
   "ProcessOID": "5e9b57f06fb31c7e65e56364",
   "ThreatLevel": 2,
   "MitreAttacks": [
    "T1060"
   ]
  },
  {
   "ProcessOID": "5e9b57c96fb31c7e65e55d26",
   "ThreatLevel": 1,
   "MitreAttacks": [
    "T1106"
   ]
  },
  {
   "ProcessOID": "5e9b57c76fb31c7e65e55666",
   "ThreatLevel": 1,
   "MitreAttacks": [
    "T1059"
   ]
  },
  {
   "ProcessOID": "5e9b57c76fb31c7e65e55665",
   "ThreatLevel": 1,
   "MitreAttacks": [
    "T1064"
   ]
  },
  {
   "ProcessOID": "5e9b57c76fb31c7e65e55665",
   "ThreatLevel": 2,
   "MitreAttacks": [
    "T1060"
   ]
  },
  {
   "ProcessOID": "5e9b57c76fb31c7e65e55665",
   "ThreatLevel": 1,
   "MitreAttacks": []
  },
  {
   "ProcessOID": "5e9b57c76fb31c7e65e55665",
   "ThreatLevel": 1,
   "MitreAttacks": []
  },
  {
   "ProcessOID": "5e9b57866fb31c7e65e55153",
   "ThreatLevel": 1,
   "MitreAttacks": [
    "T1106"
   ]
  }
 ]
}