{
 "Name": "76fri.jpg",
 "Md5": "336a4fe5d0560b25a758e62a552332da",
 "UUID": "14018d51-d9dc-46a0-a262-0211e630b25a",
 "Processes": [
  {
   "OID": "5d3a98faa6401c6266509899",
   "ProcessID": 1452,
   "ParentPID": 284,
   "CommandLine": "\"C:\\Users\\admin\\Downloads\\76fri.jpg.exe\" ",
   "Image": "C:\\Users\\admin\\Downloads\\76fri.jpg.exe",
   "ProcessType": "Main process",
   "CreationTimestamp": 1564121338203
  },
  {
   "OID": "5d3a9906a6401c626650a1d7",
   "ProcessID": 2088,
   "ParentPID": 284,
   "CommandLine": "\"C:\\Program Files\\Microsoft Office\\Office14\\WINWORD.EXE\" /n \"C:\\Users\\admin\\Desktop\\devhardcore.rtf\"",
   "Image": "C:\\Program Files\\Microsoft Office\\Office14\\WINWORD.EXE",
   "ProcessType": "Probably manual launch or APC inject",
   "CreationTimestamp": 1564121350297
  },
  {
   "OID": "5d3a9922a6401c626650bf17",
   "ProcessID": 3728,
   "ParentPID": 1452,
   "CommandLine": "\"C:\\Users\\admin\\AppData\\Roaming\\nkjhkgkjgkjgh\\hkhkhkk.exe\" 1 \"C:\\Users\\admin\\Downloads\\76fri.jpg.exe\" 1909F9",
   "Image": "C:\\Users\\admin\\AppData\\Roaming\\nkjhkgkjgkjgh\\hkhkhkk.exe",
   "ProcessType": "Child process",
   "CreationTimestamp": 1564121378234
  },
  {
   "OID": "5d3a9922a6401c626650bf18",
   "ProcessID": 3824,
   "ParentPID": 1452,
   "CommandLine": "\"C:\\Users\\admin\\AppData\\Roaming\\nkjhkgkjgkjgh\\hkhkhkk.exe\"",
   "Image": "C:\\Users\\admin\\AppData\\Roaming\\nkjhkgkjgkjgh\\hkhkhkk.exe",
   "ProcessType": "Child process",
   "CreationTimestamp": 1564121378250
  },
  {
   "OID": "5d3a9952a6401c626650c67a",
   "ProcessID": 2156,
   "ParentPID": 3824,
   "CommandLine": "\"C:\\Users\\admin\\AppData\\Roaming\\nkjhkgkjgkjgh\\hkhkhkk.exe\"",
   "Image": "C:\\Users\\admin\\AppData\\Roaming\\nkjhkgkjgkjgh\\hkhkhkk.exe",
   "ProcessType": "Child process",
   "CreationTimestamp": 1564121426078
  }
 ],
 "Incidents": [
  {
   "ProcessOID": "5d3a9952a6401c626650c67a",
   "ThreatLevel": 1,
   "MitreAttacks": []
  },
  {
   "ProcessOID": "5d3a9952a6401c626650c67a",
   "ThreatLevel": 2,
   "MitreAttacks": []
  },
  {
   "ProcessOID": "5d3a9952a6401c626650c67a",
   "ThreatLevel": 2,
   "MitreAttacks": []
  },
  {
   "ProcessOID": "5d3a9952a6401c626650c67a",
   "ThreatLevel": 1,
   "MitreAttacks": []
  },
  {
   "ProcessOID": "5d3a9952a6401c626650c67a",
   "ThreatLevel": 2,
   "MitreAttacks": [
    "T1081"
   ]
  },
  {
   "ProcessOID": "5d3a9952a6401c626650c67a",
   "ThreatLevel": 1,
   "MitreAttacks": []
  },
  {
   "ProcessOID": "5d3a9922a6401c626650bf18",
   "ThreatLevel": 1,
   "MitreAttacks": [
    "T1106"
   ]
  },
  {
   "ProcessOID": "5d3a98faa6401c6266509899",
   "ThreatLevel": 1,
   "MitreAttacks": [
    "T1106"
   ]
  },
  {
   "ProcessOID": "5d3a98faa6401c6266509899",
   "ThreatLevel": 1,
   "MitreAttacks": []
  },
  {
   "ProcessOID": "5d3a98faa6401c6266509899",
   "ThreatLevel": 1,
   "MitreAttacks": []
  },
  {
   "ProcessOID": "5d3a9909a6401c626650ac08",
   "ThreatLevel": 2,
   "MitreAttacks": [
    "T1053"
   ]
  },
  {
   "ProcessOID": "5d3a98faa6401c626650988f",
   "ThreatLevel": 1,
   "MitreAttacks": []
  },
  {
   "ProcessOID": "5d3a9906a6401c626650a1d7",
   "ThreatLevel": 0,
   "MitreAttacks": []
  },
  {
   "ProcessOID": "5d3a9906a6401c626650a1d7",
   "ThreatLevel": 0,
   "MitreAttacks": [
    "T1012"
   ]
  },
  {
   "ProcessOID": "5d3a98faa6401c626650988d",
   "ThreatLevel": 1,
   "MitreAttacks": [
    "T1012"
   ]
  },
  {
   "ProcessOID": "5d3a98faa6401c626650988d",
   "ThreatLevel": 1,
   "MitreAttacks": []
  },
  {
   "ProcessOID": "5d3a98faa6401c626650988d",
   "ThreatLevel": 0,
   "MitreAttacks": []
  },
  {
   "ProcessOID": "5d3a9906a6401c626650a1d7",
   "ThreatLevel": 0,
   "MitreAttacks": [
    "T1204"
   ]
  }
 ]
}