{
 "Name": "PI344555223.exe",
 "Md5": "36bdaaff73891c031a33fbd1508f25ef",
 "UUID": "32a04562-f7e0-4980-b168-4443e8f9466b",
 "Processes": [
  {
   "OID": "5d80dff10c2d0c4be7659619",
   "ProcessID": 3808,
   "ParentPID": 276,
   "CommandLine": "\"C:\\Users\\admin\\Desktop\\PI344555223.exe\" ",
   "Image": "C:\\Users\\admin\\Desktop\\PI344555223.exe",
   "ProcessType": "Main process",
   "CreationTimestamp": 1568727025106
  },
  {
   "OID": "5d80e0020c2d0c4be7659d40",
   "ProcessID": 2492,
   "ParentPID": 3808,
   "CommandLine": "\"C:\\Users\\admin\\Desktop\\PI344555223.exe\" ",
   "Image": "C:\\Users\\admin\\Desktop\\PI344555223.exe",
   "ProcessType": "Child process",
   "CreationTimestamp": 1568727042028
  },
  {
   "OID": "5d80e0020c2d0c4be7659d41",
   "ProcessID": 2552,
   "ParentPID": 3808,
   "CommandLine": "\"C:\\Users\\admin\\Desktop\\PI344555223.exe\" 2 2492 1498375",
   "Image": "C:\\Users\\admin\\Desktop\\PI344555223.exe",
   "ProcessType": "Child process",
   "CreationTimestamp": 1568727042028
  }
 ],
 "Incidents": [
  {
   "ProcessOID": "5d80e0020c2d0c4be7659d40",
   "ThreatLevel": 1,
   "MitreAttacks": []
  },
  {
   "ProcessOID": "5d80e0020c2d0c4be7659d40",
   "ThreatLevel": 2,
   "MitreAttacks": []
  },
  {
   "ProcessOID": "5d80e0020c2d0c4be7659d40",
   "ThreatLevel": 2,
   "MitreAttacks": []
  },
  {
   "ProcessOID": "5d80e0020c2d0c4be7659d40",
   "ThreatLevel": 2,
   "MitreAttacks": []
  },
  {
   "ProcessOID": "5d80dff10c2d0c4be7658d1e",
   "ThreatLevel": 1,
   "MitreAttacks": []
  },
  {
   "ProcessOID": "5d80e0020c2d0c4be7659d40",
   "ThreatLevel": 1,
   "MitreAttacks": []
  },
  {
   "ProcessOID": "5d80e0020c2d0c4be7659d40",
   "ThreatLevel": 2,
   "MitreAttacks": [
    "T1081"
   ]
  },
  {
   "ProcessOID": "5d80e0020c2d0c4be7659d40",
   "ThreatLevel": 1,
   "MitreAttacks": []
  },
  {
   "ProcessOID": "5d80dff10c2d0c4be7659619",
   "ThreatLevel": 1,
   "MitreAttacks": [
    "T1106"
   ]
  }
 ]
}