{
 "Name": "svchost.exe",
 "Md5": "833b90eec35a42574b53642b629e5f54",
 "UUID": "4ab22d39-0926-44d2-83f8-626b25efef09",
 "Processes": [
  {
   "OID": "5ec239ece3682951b69ef908",
   "ProcessID": 2800,
   "ParentPID": 372,
   "CommandLine": "\"C:\\Users\\admin\\AppData\\Local\\Temp\\svchost.exe\" ",
   "Image": "C:\\Users\\admin\\AppData\\Local\\Temp\\svchost.exe",
   "ProcessType": "Main process",
   "CreationTimestamp": 1589787115898
  }
 ],
 "Incidents": [
  {
   "ProcessOID": "5ec239ece3682951b69ef908",
   "ThreatLevel": 1,
   "MitreAttacks": []
  },
  {
   "ProcessOID": "5ec239ece3682951b69ef0b2",
   "ThreatLevel": 1,
   "MitreAttacks": [
    "T1012"
   ]
  }
 ]
}