{
 "Name": "109130065458_doc_________________________pdf.exe",
 "Md5": "80dc10fa4f18ca28b5a3cf7589058ba2",
 "UUID": "5f85c999-7708-40c0-bb75-8efaff9aa498",
 "Processes": [
  {
   "OID": "5cf63093097b692fbe36b25c",
   "ProcessID": 3196,
   "ParentPID": 116,
   "CommandLine": "\"C:\\Users\\admin\\AppData\\Local\\Temp\\109130065458_doc_________________________pdf.exe\" ",
   "Image": "C:\\Users\\admin\\AppData\\Local\\Temp\\109130065458_doc_________________________pdf.exe",
   "ProcessType": "Main process",
   "CreationTimestamp": 1559638162806
  },
  {
   "OID": "5cf6309f097b692fbe36b585",
   "ProcessID": 3968,
   "ParentPID": 3196,
   "CommandLine": "\u0001C:\\Users\\admin\\AppData\\Local\\Temp\\109130065458_doc_________________________pdf.exe\" ",
   "Image": "C:\\Users\\admin\\AppData\\Local\\Temp\\109130065458_doc_________________________pdf.exe",
   "ProcessType": "Child process",
   "CreationTimestamp": 1559638175447
  }
 ],
 "Incidents": [
  {
   "ProcessOID": "5cf6309f097b692fbe36b585",
   "ThreatLevel": 1,
   "MitreAttacks": []
  },
  {
   "ProcessOID": "5cf6309f097b692fbe36b585",
   "ThreatLevel": 2,
   "MitreAttacks": []
  },
  {
   "ProcessOID": "5cf6309f097b692fbe36b585",
   "ThreatLevel": 2,
   "MitreAttacks": []
  },
  {
   "ProcessOID": "5cf6309f097b692fbe36b585",
   "ThreatLevel": 2,
   "MitreAttacks": []
  },
  {
   "ProcessOID": "5cf6309f097b692fbe36b585",
   "ThreatLevel": 1,
   "MitreAttacks": []
  },
  {
   "ProcessOID": "5cf6309f097b692fbe36b585",
   "ThreatLevel": 2,
   "MitreAttacks": [
    "T1081"
   ]
  },
  {
   "ProcessOID": "5cf6309f097b692fbe36b585",
   "ThreatLevel": 1,
   "MitreAttacks": []
  },
  {
   "ProcessOID": "5cf63093097b692fbe36b25c",
   "ThreatLevel": 1,
   "MitreAttacks": [
    "T1106"
   ]
  }
 ]
}