{
 "Name": "PaymentAdviceAgisco_CS540.exe",
 "Md5": "05ae862d95759d6b44dcc6798cb8f25f",
 "UUID": "7f2ef8c4-15e0-4111-b1ed-77e6531445cf",
 "Processes": [
  {
   "OID": "5e38d5eb0f9d407e3830dbc3",
   "ProcessID": 604,
   "ParentPID": 372,
   "CommandLine": "\"C:\\Users\\admin\\AppData\\Local\\Temp\\PaymentAdviceAgisco_CS540.exe\" ",
   "Image": "C:\\Users\\admin\\AppData\\Local\\Temp\\PaymentAdviceAgisco_CS540.exe",
   "ProcessType": "Main process",
   "CreationTimestamp": 1580783082598
  },
  {
   "OID": "5e38d5ed0f9d407e3830de7a",
   "ProcessID": 3108,
   "ParentPID": 604,
   "CommandLine": "\"C:\\Users\\admin\\AppData\\Local\\Temp\\PaymentAdviceAgisco_CS540.exe\" ",
   "Image": "C:\\Users\\admin\\AppData\\Local\\Temp\\PaymentAdviceAgisco_CS540.exe",
   "ProcessType": "Child process",
   "CreationTimestamp": 1580783084661
  }
 ],
 "Incidents": [
  {
   "ProcessOID": "5e38d5ed0f9d407e3830de7a",
   "ThreatLevel": 1,
   "MitreAttacks": []
  },
  {
   "ProcessOID": "5e38d5ed0f9d407e3830de7a",
   "ThreatLevel": 2,
   "MitreAttacks": []
  },
  {
   "ProcessOID": "5e38d5ed0f9d407e3830de7a",
   "ThreatLevel": 2,
   "MitreAttacks": []
  },
  {
   "ProcessOID": "5e38d5ed0f9d407e3830de7a",
   "ThreatLevel": 2,
   "MitreAttacks": [
    "T1081"
   ]
  },
  {
   "ProcessOID": "5e38d5ed0f9d407e3830de7a",
   "ThreatLevel": 1,
   "MitreAttacks": []
  },
  {
   "ProcessOID": "5e38d5ed0f9d407e3830de7a",
   "ThreatLevel": 1,
   "MitreAttacks": []
  },
  {
   "ProcessOID": "5e38d5ed0f9d407e3830de7a",
   "ThreatLevel": 0,
   "MitreAttacks": [
    "T1012"
   ]
  },
  {
   "ProcessOID": "5e38d5ed0f9d407e3830de7a",
   "ThreatLevel": 1,
   "MitreAttacks": [
    "T1130"
   ]
  },
  {
   "ProcessOID": "5e38d5ed0f9d407e3830de7a",
   "ThreatLevel": 2,
   "MitreAttacks": [
    "T1130"
   ]
  },
  {
   "ProcessOID": "5e38d5ea0f9d407e3830d2e3",
   "ThreatLevel": 1,
   "MitreAttacks": [
    "T1012"
   ]
  },
  {
   "ProcessOID": "5e38d5ed0f9d407e3830de7a",
   "ThreatLevel": 1,
   "MitreAttacks": [
    "T1012"
   ]
  },
  {
   "ProcessOID": "5e38d5eb0f9d407e3830dbc3",
   "ThreatLevel": 1,
   "MitreAttacks": [
    "T1106"
   ]
  }
 ]
}