{
 "Name": "jack2604_2nd_ig1_9cr17.exe",
 "Md5": "edacb669432a5a21020d81aff93b4e52",
 "UUID": "8a624cb1-8141-4e48-a199-e24eda24dad6",
 "Processes": [
  {
   "OID": "5eabfe953c7c274e7e87d666",
   "ProcessID": 3504,
   "ParentPID": 372,
   "CommandLine": "\"C:\\Users\\admin\\AppData\\Local\\Temp\\jack2604_2nd_ig1_9cr17.exe\" ",
   "Image": "C:\\Users\\admin\\AppData\\Local\\Temp\\jack2604_2nd_ig1_9cr17.exe",
   "ProcessType": "Main process",
   "CreationTimestamp": 1588330132650
  }
 ],
 "Incidents": [
  {
   "ProcessOID": "5eabfe953c7c274e7e87d666",
   "ThreatLevel": 1,
   "MitreAttacks": []
  },
  {
   "ProcessOID": "5eabfe953c7c274e7e87d666",
   "ThreatLevel": 2,
   "MitreAttacks": []
  },
  {
   "ProcessOID": "5eabfe953c7c274e7e87d666",
   "ThreatLevel": 1,
   "MitreAttacks": []
  },
  {
   "ProcessOID": "5eabfe943c7c274e7e87ceaf",
   "ThreatLevel": 1,
   "MitreAttacks": [
    "T1012"
   ]
  },
  {
   "ProcessOID": "5eabfe953c7c274e7e87d666",
   "ThreatLevel": 2,
   "MitreAttacks": [
    "T1081"
   ]
  },
  {
   "ProcessOID": "5eabfe953c7c274e7e87d666",
   "ThreatLevel": 1,
   "MitreAttacks": []
  }
 ]
}