{
 "Name": "LETTER_of_Complaint.exe",
 "Md5": "7f112da59f3f4b3878e4bd0ecac597d5",
 "UUID": "cc404bf8-9d2b-4086-b8ce-f3dec01a9cc8",
 "Processes": [
  {
   "OID": "5dccb4b6d8105e3409c8ff2a",
   "ProcessID": 2456,
   "ParentPID": 352,
   "CommandLine": "\"C:\\Users\\admin\\AppData\\Local\\Temp\\LETTER_of_Complaint.exe\" ",
   "Image": "C:\\Users\\admin\\AppData\\Local\\Temp\\LETTER_of_Complaint.exe",
   "ProcessType": "Main process",
   "CreationTimestamp": 1573696694397
  },
  {
   "OID": "5dccb4d2d8105e3409c90b31",
   "ProcessID": 3456,
   "ParentPID": 2456,
   "CommandLine": "\"C:\\Windows\\Microsoft.NET\\Framework\\v4.0.30319\\RegAsm.exe\"",
   "Image": "C:\\Windows\\Microsoft.NET\\Framework\\v4.0.30319\\RegAsm.exe",
   "ProcessType": "Child process",
   "CreationTimestamp": 1573696721897
  }
 ],
 "Incidents": [
  {
   "ProcessOID": "5dccb4d2d8105e3409c90b31",
   "ThreatLevel": 2,
   "MitreAttacks": []
  },
  {
   "ProcessOID": "5dccb4d2d8105e3409c90b31",
   "ThreatLevel": 1,
   "MitreAttacks": []
  },
  {
   "ProcessOID": "5dccb4d2d8105e3409c90b31",
   "ThreatLevel": 2,
   "MitreAttacks": []
  },
  {
   "ProcessOID": "5dccb4d2d8105e3409c90b31",
   "ThreatLevel": 1,
   "MitreAttacks": []
  },
  {
   "ProcessOID": "5dccb4d2d8105e3409c90b31",
   "ThreatLevel": 1,
   "MitreAttacks": []
  },
  {
   "ProcessOID": "5dccb4d2d8105e3409c90b31",
   "ThreatLevel": 2,
   "MitreAttacks": []
  },
  {
   "ProcessOID": "5dccb4d2d8105e3409c90b31",
   "ThreatLevel": 2,
   "MitreAttacks": [
    "T1081"
   ]
  },
  {
   "ProcessOID": "5dccb4d2d8105e3409c90b31",
   "ThreatLevel": 1,
   "MitreAttacks": []
  }
 ]
}