{
 "Name": "e3387033890ff9d5cb3786fde1684cf79795adab8749fd7c41b412e711ae7979",
 "Md5": "adca8f84c76417aeb58c3c0c1a8aa4c5",
 "UUID": "f41ea8c6-c5b7-4c5e-9b59-098cedc670ac",
 "Processes": [
  {
   "OID": "5ef463d8e0a7982bf33cc8c0",
   "ProcessID": 2388,
   "ParentPID": 308,
   "CommandLine": "\"C:\\Users\\admin\\AppData\\Local\\Temp\\e3387033890ff9d5cb3786fde1684cf79795adab8749fd7c41b412e711ae7979.exe\" ",
   "Image": "C:\\Users\\admin\\AppData\\Local\\Temp\\e3387033890ff9d5cb3786fde1684cf79795adab8749fd7c41b412e711ae7979.exe",
   "ProcessType": "Main process",
   "CreationTimestamp": 1593074648123
  },
  {
   "OID": "5ef463d9e0a7982bf33cca29",
   "ProcessID": 764,
   "ParentPID": 2388,
   "CommandLine": "\"{path}\"",
   "Image": "C:\\Windows\\Microsoft.NET\\Framework\\v2.0.50727\\vbc.exe",
   "ProcessType": "Child process",
   "CreationTimestamp": 1593074648998
  }
 ],
 "Incidents": [
  {
   "ProcessOID": "5ef463d9e0a7982bf33cca29",
   "ThreatLevel": 2,
   "MitreAttacks": []
  },
  {
   "ProcessOID": "5ef463d9e0a7982bf33cca29",
   "ThreatLevel": 1,
   "MitreAttacks": []
  },
  {
   "ProcessOID": "5ef463d9e0a7982bf33cca29",
   "ThreatLevel": 2,
   "MitreAttacks": []
  },
  {
   "ProcessOID": "5ef463d9e0a7982bf33cca29",
   "ThreatLevel": 1,
   "MitreAttacks": []
  },
  {
   "ProcessOID": "5ef463d8e0a7982bf33cc14d",
   "ThreatLevel": 1,
   "MitreAttacks": [
    "T1012"
   ]
  },
  {
   "ProcessOID": "5ef463d9e0a7982bf33cca29",
   "ThreatLevel": 2,
   "MitreAttacks": [
    "T1081"
   ]
  },
  {
   "ProcessOID": "5ef463d9e0a7982bf33cca29",
   "ThreatLevel": 1,
   "MitreAttacks": []
  },
  {
   "ProcessOID": "5ef463d8e0a7982bf33cc8c0",
   "ThreatLevel": 1,
   "MitreAttacks": [
    "T1064"
   ]
  }
 ]
}