{
 "Name": "Puchase Order_Dubai.img.exe",
 "Md5": "e7d8a49e48e013499e9549166f61b275",
 "UUID": "f789a6db-19e3-4299-ac08-074c1092fcc9",
 "Processes": [
  {
   "OID": "5e31dbc186367529f349ea8d",
   "ProcessID": 3316,
   "ParentPID": 372,
   "CommandLine": "\"C:\\Users\\admin\\AppData\\Local\\Temp\\Puchase Order_Dubai.img.exe\" ",
   "Image": "C:\\Users\\admin\\AppData\\Local\\Temp\\Puchase Order_Dubai.img.exe",
   "ProcessType": "Main process",
   "CreationTimestamp": 1580325824825
  },
  {
   "OID": "5e31dbc686367529f349f3ec",
   "ProcessID": 4004,
   "ParentPID": 3316,
   "CommandLine": "\"C:\\Users\\admin\\AppData\\Local\\Temp\\Puchase Order_Dubai.img.exe\" ",
   "Image": "C:\\Users\\admin\\AppData\\Local\\Temp\\Puchase Order_Dubai.img.exe",
   "ProcessType": "Child process",
   "CreationTimestamp": 1580325830278
  }
 ],
 "Incidents": [
  {
   "ProcessOID": "5e31dbc686367529f349f3ec",
   "ThreatLevel": 2,
   "MitreAttacks": []
  },
  {
   "ProcessOID": "5e31dbc686367529f349f3ec",
   "ThreatLevel": 1,
   "MitreAttacks": []
  },
  {
   "ProcessOID": "5e31dbc686367529f349f3ec",
   "ThreatLevel": 2,
   "MitreAttacks": []
  },
  {
   "ProcessOID": "5e31dbc686367529f349f3ec",
   "ThreatLevel": 2,
   "MitreAttacks": [
    "T1081"
   ]
  },
  {
   "ProcessOID": "5e31dbc686367529f349f3ec",
   "ThreatLevel": 1,
   "MitreAttacks": []
  },
  {
   "ProcessOID": "5e31dbc686367529f349f3ec",
   "ThreatLevel": 1,
   "MitreAttacks": []
  },
  {
   "ProcessOID": "5e31dbc686367529f349f3ec",
   "ThreatLevel": 0,
   "MitreAttacks": [
    "T1012"
   ]
  },
  {
   "ProcessOID": "5e31dbc686367529f349f3ec",
   "ThreatLevel": 1,
   "MitreAttacks": [
    "T1130"
   ]
  },
  {
   "ProcessOID": "5e31dbc686367529f349f3ec",
   "ThreatLevel": 2,
   "MitreAttacks": [
    "T1130"
   ]
  },
  {
   "ProcessOID": "5e31dbc186367529f349ea81",
   "ThreatLevel": 1,
   "MitreAttacks": [
    "T1012"
   ]
  },
  {
   "ProcessOID": "5e31dbc686367529f349f3ec",
   "ThreatLevel": 1,
   "MitreAttacks": [
    "T1012"
   ]
  },
  {
   "ProcessOID": "5e31dbc186367529f349ea8d",
   "ThreatLevel": 1,
   "MitreAttacks": [
    "T1106"
   ]
  }
 ]
}