{
 "Name": "93198dee8a8fd1576af750d7a89dcbc56d21aebfd5ae632660f7b65d3558842b",
 "Md5": "9b361211a5ec0e5c12869e1b246e4d96",
 "UUID": "00f812be-22b1-4679-a748-d8e048d51613",
 "Processes": [
  {
   "OID": "5e542f517aa12d4a2c3b3ac6",
   "ProcessID": 3604,
   "ParentPID": 372,
   "CommandLine": "\"C:\\Users\\admin\\AppData\\Local\\Temp\\93198dee8a8fd1576af750d7a89dcbc56d21aebfd5ae632660f7b65d3558842b.exe\" ",
   "Image": "C:\\Users\\admin\\AppData\\Local\\Temp\\93198dee8a8fd1576af750d7a89dcbc56d21aebfd5ae632660f7b65d3558842b.exe",
   "ProcessType": "Main process",
   "CreationTimestamp": 1582575440955
  },
  {
   "OID": "5e542f597aa12d4a2c3b45d0",
   "ProcessID": 2124,
   "ParentPID": 3604,
   "CommandLine": "\"C:\\Users\\admin\\AppData\\Local\\grpconv\\grpconv.exe\"",
   "Image": "C:\\Users\\admin\\AppData\\Local\\grpconv\\grpconv.exe",
   "ProcessType": "Child process",
   "CreationTimestamp": 1582575449111
  }
 ],
 "Incidents": [
  {
   "ProcessOID": "5e542f597aa12d4a2c3b45d0",
   "ThreatLevel": 1,
   "MitreAttacks": []
  },
  {
   "ProcessOID": "5e542f597aa12d4a2c3b45d0",
   "ThreatLevel": 2,
   "MitreAttacks": []
  },
  {
   "ProcessOID": "5e542f597aa12d4a2c3b45d0",
   "ThreatLevel": 2,
   "MitreAttacks": []
  },
  {
   "ProcessOID": "5e542f517aa12d4a2c3b3abb",
   "ThreatLevel": 1,
   "MitreAttacks": [
    "T1012"
   ]
  },
  {
   "ProcessOID": "5e542f597aa12d4a2c3b45d0",
   "ThreatLevel": 1,
   "MitreAttacks": [
    "T1012"
   ]
  },
  {
   "ProcessOID": "5e542f517aa12d4a2c3b3ac6",
   "ThreatLevel": 1,
   "MitreAttacks": []
  },
  {
   "ProcessOID": "5e542f517aa12d4a2c3b3ac6",
   "ThreatLevel": 2,
   "MitreAttacks": []
  },
  {
   "ProcessOID": "5e542f517aa12d4a2c3b3ac6",
   "ThreatLevel": 1,
   "MitreAttacks": [
    "T1106"
   ]
  }
 ]
}