{
 "Name": "Petrovic.exe",
 "Md5": "578bc61e4453fffd9324d730de1f3d4f",
 "UUID": "0c30cf75-ac62-477d-8e8b-342523247acc",
 "Processes": [
  {
   "OID": "5e8718c8c430ae270a4318b2",
   "ProcessID": 1852,
   "ParentPID": 372,
   "CommandLine": "\"C:\\Users\\admin\\AppData\\Local\\Temp\\Petrovic.exe\" ",
   "Image": "C:\\Users\\admin\\AppData\\Local\\Temp\\Petrovic.exe",
   "ProcessType": "Main process",
   "CreationTimestamp": 1585912008132
  },
  {
   "OID": "5e8718cbc430ae270a432257",
   "ProcessID": 3168,
   "ParentPID": 1852,
   "CommandLine": "\"C:\\Users\\admin\\AppData\\Local\\vcomp100\\vcomp100.exe\"",
   "Image": "C:\\Users\\admin\\AppData\\Local\\vcomp100\\vcomp100.exe",
   "ProcessType": "Child process",
   "CreationTimestamp": 1585912011366
  },
  {
   "OID": "5e8718dbc430ae270a43285b",
   "ProcessID": 3140,
   "ParentPID": 3168,
   "CommandLine": "\"C:\\ProgramData\\rKRjRP.exe\"",
   "Image": "C:\\ProgramData\\rKRjRP.exe",
   "ProcessType": "Child process",
   "CreationTimestamp": 1585912027679
  },
  {
   "OID": "5e8718ddc430ae270a432a8a",
   "ProcessID": 3228,
   "ParentPID": 3140,
   "CommandLine": "\"C:\\Users\\admin\\AppData\\Local\\vcomp100\\vcomp100.exe\"",
   "Image": "C:\\Users\\admin\\AppData\\Local\\vcomp100\\vcomp100.exe",
   "ProcessType": "Child process",
   "CreationTimestamp": 1585912028851
  }
 ],
 "Incidents": [
  {
   "ProcessOID": "5e8718ddc430ae270a432a8a",
   "ThreatLevel": 2,
   "MitreAttacks": [
    "T1060"
   ]
  },
  {
   "ProcessOID": "5e8718ddc430ae270a432a8a",
   "ThreatLevel": 1,
   "MitreAttacks": []
  },
  {
   "ProcessOID": "5e8718ddc430ae270a432a8a",
   "ThreatLevel": 2,
   "MitreAttacks": []
  },
  {
   "ProcessOID": "5e8718ddc430ae270a432a8a",
   "ThreatLevel": 2,
   "MitreAttacks": []
  },
  {
   "ProcessOID": "5e8718ddc430ae270a432a8a",
   "ThreatLevel": 1,
   "MitreAttacks": [
    "T1012"
   ]
  },
  {
   "ProcessOID": "5e8718dbc430ae270a43285b",
   "ThreatLevel": 2,
   "MitreAttacks": []
  },
  {
   "ProcessOID": "5e8718ddc430ae270a432a8a",
   "ThreatLevel": 2,
   "MitreAttacks": []
  },
  {
   "ProcessOID": "5e8718dbc430ae270a43285b",
   "ThreatLevel": 1,
   "MitreAttacks": [
    "T1106"
   ]
  },
  {
   "ProcessOID": "5e8718dbc430ae270a43285b",
   "ThreatLevel": 1,
   "MitreAttacks": []
  },
  {
   "ProcessOID": "5e8718dbc430ae270a43285b",
   "ThreatLevel": 2,
   "MitreAttacks": []
  },
  {
   "ProcessOID": "5e8718cbc430ae270a432257",
   "ThreatLevel": 1,
   "MitreAttacks": []
  },
  {
   "ProcessOID": "5e8718cbc430ae270a432257",
   "ThreatLevel": 2,
   "MitreAttacks": [
    "T1060"
   ]
  },
  {
   "ProcessOID": "5e8718cbc430ae270a432257",
   "ThreatLevel": 1,
   "MitreAttacks": []
  },
  {
   "ProcessOID": "5e8718cbc430ae270a432257",
   "ThreatLevel": 2,
   "MitreAttacks": []
  },
  {
   "ProcessOID": "5e8718cbc430ae270a432257",
   "ThreatLevel": 2,
   "MitreAttacks": []
  },
  {
   "ProcessOID": "5e8718c8c430ae270a4318a6",
   "ThreatLevel": 1,
   "MitreAttacks": [
    "T1012"
   ]
  },
  {
   "ProcessOID": "5e8718cbc430ae270a432257",
   "ThreatLevel": 1,
   "MitreAttacks": [
    "T1012"
   ]
  },
  {
   "ProcessOID": "5e8718c8c430ae270a4318b2",
   "ThreatLevel": 2,
   "MitreAttacks": []
  },
  {
   "ProcessOID": "5e8718c8c430ae270a4318b2",
   "ThreatLevel": 1,
   "MitreAttacks": [
    "T1106"
   ]
  },
  {
   "ProcessOID": "5e8718c8c430ae270a4318b2",
   "ThreatLevel": 1,
   "MitreAttacks": []
  }
 ]
}