{
 "Name": "ayQUtnd403",
 "Md5": "da552dba5103148a3ff7d97e0a5ff542",
 "UUID": "1af722a1-8e74-44e1-a7ab-abe380d98b2c",
 "Processes": [
  {
   "OID": "5f45f003757edd7b8a86937d",
   "ProcessID": 2796,
   "ParentPID": 1704,
   "CommandLine": "\"C:\\Users\\admin\\AppData\\Local\\Temp\\ayQUtnd403.exe\" ",
   "Image": "C:\\Users\\admin\\AppData\\Local\\Temp\\ayQUtnd403.exe",
   "ProcessType": "Main process",
   "CreationTimestamp": 1598418946848
  },
  {
   "OID": "5f45f003757edd7b8a869a0d",
   "ProcessID": 2508,
   "ParentPID": 2796,
   "CommandLine": "\"C:\\Users\\admin\\AppData\\Local\\fveprompt\\RacEngn.exe\"",
   "Image": "C:\\Users\\admin\\AppData\\Local\\fveprompt\\RacEngn.exe",
   "ProcessType": "Child process",
   "CreationTimestamp": 1598418947317
  }
 ],
 "Incidents": [
  {
   "ProcessOID": "5f45f003757edd7b8a869a0d",
   "ThreatLevel": 2,
   "MitreAttacks": []
  },
  {
   "ProcessOID": "5f45f003757edd7b8a869a0d",
   "ThreatLevel": 2,
   "MitreAttacks": []
  },
  {
   "ProcessOID": "5f45f003757edd7b8a869a0d",
   "ThreatLevel": 2,
   "MitreAttacks": [
    "T1060"
   ]
  },
  {
   "ProcessOID": "5f45f003757edd7b8a86936e",
   "ThreatLevel": 1,
   "MitreAttacks": [
    "T1012"
   ]
  },
  {
   "ProcessOID": "5f45f003757edd7b8a869a0d",
   "ThreatLevel": 1,
   "MitreAttacks": [
    "T1012"
   ]
  },
  {
   "ProcessOID": "5f45f003757edd7b8a86937d",
   "ThreatLevel": 1,
   "MitreAttacks": [
    "T1106"
   ]
  },
  {
   "ProcessOID": "5f45f003757edd7b8a86937d",
   "ThreatLevel": 1,
   "MitreAttacks": []
  }
 ]
}