{
 "Name": "Qp4_r4.exe",
 "Md5": "364ab2e098d174ab57b1926b7aca75dc",
 "UUID": "223794fd-248f-49b1-bc53-f8f0708926d6",
 "Processes": [
  {
   "OID": "5f464cfc711dc11dec1c524b",
   "ProcessID": 2880,
   "ParentPID": 1704,
   "CommandLine": "\"C:\\Users\\admin\\Desktop\\Qp4_r4.exe\" ",
   "Image": "C:\\Users\\admin\\Desktop\\Qp4_r4.exe",
   "ProcessType": "Main process",
   "CreationTimestamp": 1598442748234
  },
  {
   "OID": "5f464cfc711dc11dec1c58db",
   "ProcessID": 2240,
   "ParentPID": 2880,
   "CommandLine": "\"C:\\Users\\admin\\AppData\\Local\\iepeers\\reg.exe\"",
   "Image": "C:\\Users\\admin\\AppData\\Local\\iepeers\\reg.exe",
   "ProcessType": "Child process",
   "CreationTimestamp": 1598442748562
  }
 ],
 "Incidents": [
  {
   "ProcessOID": "5f464cfc711dc11dec1c58db",
   "ThreatLevel": 1,
   "MitreAttacks": []
  },
  {
   "ProcessOID": "5f464cfc711dc11dec1c523a",
   "ThreatLevel": 1,
   "MitreAttacks": []
  },
  {
   "ProcessOID": "5f464cfc711dc11dec1c58db",
   "ThreatLevel": 2,
   "MitreAttacks": []
  },
  {
   "ProcessOID": "5f464cfc711dc11dec1c58db",
   "ThreatLevel": 2,
   "MitreAttacks": []
  },
  {
   "ProcessOID": "5f464cfc711dc11dec1c523c",
   "ThreatLevel": 1,
   "MitreAttacks": [
    "T1012"
   ]
  },
  {
   "ProcessOID": "5f464cfc711dc11dec1c58db",
   "ThreatLevel": 1,
   "MitreAttacks": [
    "T1012"
   ]
  },
  {
   "ProcessOID": "5f464cfc711dc11dec1c524b",
   "ThreatLevel": 1,
   "MitreAttacks": []
  },
  {
   "ProcessOID": "5f464cfc711dc11dec1c524b",
   "ThreatLevel": 1,
   "MitreAttacks": [
    "T1106"
   ]
  }
 ]
}