{
 "Name": "em3.exe",
 "Md5": "c0de01d11d724f35ad32ec2ad5abf476",
 "UUID": "32cfa358-d0b9-4768-83f5-8f1ab8310d54",
 "Processes": [
  {
   "OID": "5e6be3e10c6019713c56fcaf",
   "ProcessID": 1740,
   "ParentPID": 372,
   "CommandLine": "\"C:\\Users\\admin\\AppData\\Local\\Temp\\em3.exe\" ",
   "Image": "C:\\Users\\admin\\AppData\\Local\\Temp\\em3.exe",
   "ProcessType": "Main process",
   "CreationTimestamp": 1584128992685
  },
  {
   "OID": "5e6be3e70c6019713c570624",
   "ProcessID": 3420,
   "ParentPID": 1740,
   "CommandLine": "\"C:\\Users\\admin\\AppData\\Local\\msimg32\\msimg32.exe\"",
   "Image": "C:\\Users\\admin\\AppData\\Local\\msimg32\\msimg32.exe",
   "ProcessType": "Child process",
   "CreationTimestamp": 1584128999607
  },
  {
   "OID": "5e6be3fb0c6019713c570bee",
   "ProcessID": 3012,
   "ParentPID": 3420,
   "CommandLine": "\"C:\\ProgramData\\BBLpmLrpKLBBUTFqufE.exe\"",
   "Image": "C:\\ProgramData\\BBLpmLrpKLBBUTFqufE.exe",
   "ProcessType": "Child process",
   "CreationTimestamp": 1584129019123
  },
  {
   "OID": "5e6be4000c6019713c570e4f",
   "ProcessID": 3140,
   "ParentPID": 3012,
   "CommandLine": "\"C:\\Users\\admin\\AppData\\Local\\msimg32\\msimg32.exe\"",
   "Image": "C:\\Users\\admin\\AppData\\Local\\msimg32\\msimg32.exe",
   "ProcessType": "Child process",
   "CreationTimestamp": 1584129023435
  }
 ],
 "Incidents": [
  {
   "ProcessOID": "5e6be4000c6019713c570e4f",
   "ThreatLevel": 2,
   "MitreAttacks": []
  },
  {
   "ProcessOID": "5e6be4000c6019713c570e4f",
   "ThreatLevel": 2,
   "MitreAttacks": []
  },
  {
   "ProcessOID": "5e6be4000c6019713c570e4f",
   "ThreatLevel": 2,
   "MitreAttacks": [
    "T1060"
   ]
  },
  {
   "ProcessOID": "5e6be4000c6019713c570e4f",
   "ThreatLevel": 1,
   "MitreAttacks": []
  },
  {
   "ProcessOID": "5e6be4000c6019713c570e4f",
   "ThreatLevel": 1,
   "MitreAttacks": [
    "T1012"
   ]
  },
  {
   "ProcessOID": "5e6be4000c6019713c570e4f",
   "ThreatLevel": 2,
   "MitreAttacks": []
  },
  {
   "ProcessOID": "5e6be3fb0c6019713c570bee",
   "ThreatLevel": 2,
   "MitreAttacks": []
  },
  {
   "ProcessOID": "5e6be3fb0c6019713c570bee",
   "ThreatLevel": 1,
   "MitreAttacks": [
    "T1106"
   ]
  },
  {
   "ProcessOID": "5e6be3fb0c6019713c570bee",
   "ThreatLevel": 1,
   "MitreAttacks": []
  },
  {
   "ProcessOID": "5e6be3fb0c6019713c570bee",
   "ThreatLevel": 2,
   "MitreAttacks": []
  },
  {
   "ProcessOID": "5e6be3e70c6019713c570624",
   "ThreatLevel": 1,
   "MitreAttacks": []
  },
  {
   "ProcessOID": "5e6be3e70c6019713c570624",
   "ThreatLevel": 1,
   "MitreAttacks": []
  },
  {
   "ProcessOID": "5e6be3e70c6019713c570624",
   "ThreatLevel": 2,
   "MitreAttacks": [
    "T1060"
   ]
  },
  {
   "ProcessOID": "5e6be3e70c6019713c570624",
   "ThreatLevel": 2,
   "MitreAttacks": []
  },
  {
   "ProcessOID": "5e6be3e70c6019713c570624",
   "ThreatLevel": 2,
   "MitreAttacks": []
  },
  {
   "ProcessOID": "5e6be3e70c6019713c570624",
   "ThreatLevel": 1,
   "MitreAttacks": []
  },
  {
   "ProcessOID": "5e6be3e10c6019713c56fca4",
   "ThreatLevel": 1,
   "MitreAttacks": [
    "T1012"
   ]
  },
  {
   "ProcessOID": "5e6be3e70c6019713c570624",
   "ThreatLevel": 1,
   "MitreAttacks": [
    "T1012"
   ]
  },
  {
   "ProcessOID": "5e6be3e10c6019713c56fcaf",
   "ThreatLevel": 2,
   "MitreAttacks": []
  },
  {
   "ProcessOID": "5e6be3e10c6019713c56fcaf",
   "ThreatLevel": 1,
   "MitreAttacks": [
    "T1106"
   ]
  },
  {
   "ProcessOID": "5e6be3e10c6019713c56fcaf",
   "ThreatLevel": 1,
   "MitreAttacks": []
  }
 ]
}