{
 "Name": "E2-20200703_164201",
 "Md5": "83581d4b5e4c8228e054176b838841d5",
 "UUID": "54406073-e9b6-43b9-9350-19f9ae6510fa",
 "Processes": [
  {
   "OID": "5f0037ad2e65a04229b5afe0",
   "ProcessID": 2132,
   "ParentPID": 1688,
   "CommandLine": "\"C:\\Users\\admin\\Desktop\\E2-20200703_164201.exe\" ",
   "Image": "C:\\Users\\admin\\Desktop\\E2-20200703_164201.exe",
   "ProcessType": "Main process",
   "CreationTimestamp": 1593849773462
  },
  {
   "OID": "5f0037b32e65a04229b5b6a4",
   "ProcessID": 1512,
   "ParentPID": 2132,
   "CommandLine": "\"C:\\Users\\admin\\AppData\\Local\\aelupsvc\\mfc100fra.exe\"",
   "Image": "C:\\Users\\admin\\AppData\\Local\\aelupsvc\\mfc100fra.exe",
   "ProcessType": "Child process",
   "CreationTimestamp": 1593849779431
  }
 ],
 "Incidents": [
  {
   "ProcessOID": "5f0037b32e65a04229b5b6a4",
   "ThreatLevel": 1,
   "MitreAttacks": []
  },
  {
   "ProcessOID": "5f0037b32e65a04229b5b6a4",
   "ThreatLevel": 2,
   "MitreAttacks": [
    "T1060"
   ]
  },
  {
   "ProcessOID": "5f0037b32e65a04229b5b6a4",
   "ThreatLevel": 2,
   "MitreAttacks": []
  },
  {
   "ProcessOID": "5f0037b32e65a04229b5b6a4",
   "ThreatLevel": 2,
   "MitreAttacks": []
  },
  {
   "ProcessOID": "5f0037ad2e65a04229b5a7b2",
   "ThreatLevel": 1,
   "MitreAttacks": [
    "T1012"
   ]
  },
  {
   "ProcessOID": "5f0037b32e65a04229b5b6a4",
   "ThreatLevel": 1,
   "MitreAttacks": [
    "T1012"
   ]
  },
  {
   "ProcessOID": "5f0037ad2e65a04229b5afe0",
   "ThreatLevel": 1,
   "MitreAttacks": [
    "T1106"
   ]
  },
  {
   "ProcessOID": "5f0037ad2e65a04229b5afe0",
   "ThreatLevel": 1,
   "MitreAttacks": []
  }
 ]
}