{
 "Name": "uT068804",
 "Md5": "0594caeb40b2f65a5a76d3b749dc4693",
 "UUID": "5574a4a1-cd63-499c-96df-66e94090ba46",
 "Processes": [
  {
   "OID": "5e2adba0d96af8134d7875bb",
   "ProcessID": 3580,
   "ParentPID": 372,
   "CommandLine": "\"C:\\Users\\admin\\AppData\\Local\\Temp\\uT068804.exe\" ",
   "Image": "C:\\Users\\admin\\AppData\\Local\\Temp\\uT068804.exe",
   "ProcessType": "Main process",
   "CreationTimestamp": 1579867040042
  },
  {
   "OID": "5e2adba0d96af8134d7875bc",
   "ProcessID": 4052,
   "ParentPID": 3580,
   "CommandLine": "--abf0670d",
   "Image": "C:\\Users\\admin\\AppData\\Local\\Temp\\uT068804.exe",
   "ProcessType": "Child process",
   "CreationTimestamp": 1579867040136
  },
  {
   "OID": "5e2adba7d96af8134d7879bd",
   "ProcessID": 2948,
   "ParentPID": 4052,
   "CommandLine": "\"C:\\Users\\admin\\AppData\\Local\\pdeftvolume\\pdeftvolume.exe\"",
   "Image": "C:\\Users\\admin\\AppData\\Local\\pdeftvolume\\pdeftvolume.exe",
   "ProcessType": "Child process",
   "CreationTimestamp": 1579867046745
  },
  {
   "OID": "5e2adba7d96af8134d7879be",
   "ProcessID": 2116,
   "ParentPID": 2948,
   "CommandLine": "--a66f8ff2",
   "Image": "C:\\Users\\admin\\AppData\\Local\\pdeftvolume\\pdeftvolume.exe",
   "ProcessType": "Child process",
   "CreationTimestamp": 1579867046839
  }
 ],
 "Incidents": [
  {
   "ProcessOID": "5e2adba7d96af8134d7879be",
   "ThreatLevel": 2,
   "MitreAttacks": [
    "T1060"
   ]
  },
  {
   "ProcessOID": "5e2adba7d96af8134d7879be",
   "ThreatLevel": 1,
   "MitreAttacks": []
  },
  {
   "ProcessOID": "5e2adba7d96af8134d7879be",
   "ThreatLevel": 2,
   "MitreAttacks": []
  },
  {
   "ProcessOID": "5e2adba7d96af8134d7879be",
   "ThreatLevel": 2,
   "MitreAttacks": []
  },
  {
   "ProcessOID": "5e2adba0d96af8134d786e55",
   "ThreatLevel": 1,
   "MitreAttacks": [
    "T1012"
   ]
  },
  {
   "ProcessOID": "5e2adba7d96af8134d7879be",
   "ThreatLevel": 1,
   "MitreAttacks": [
    "T1012"
   ]
  },
  {
   "ProcessOID": "5e2adba0d96af8134d7875bc",
   "ThreatLevel": 2,
   "MitreAttacks": []
  },
  {
   "ProcessOID": "5e2adba0d96af8134d7875bc",
   "ThreatLevel": 1,
   "MitreAttacks": [
    "T1106"
   ]
  },
  {
   "ProcessOID": "5e2adba0d96af8134d7875bc",
   "ThreatLevel": 1,
   "MitreAttacks": []
  }
 ]
}